[
    {
        "id":1,"name":" Lara Smith","designation":"Engineer",
        "qoute":"I appreciate the Dental solution. I am happy getting good traeatment. The have a good team. Really this is then best",
        "img":"https://health-center.vamtam.com/wp-content/uploads/2013/07/tes2.jpg"

    },
    {
        "id":2,"name":"Watson","designation":"Engineer",
        "qoute":"I appreciate the Dental solution. I am happy getting good traeatment. The have a good team. Really this is then best",
        "img":"https://health-center.vamtam.com/wp-content/uploads/2013/07/tes3.jpg"
    },
    {
        "id":3,"name":"Angelina","designation":"Engineer",
        "qoute":"I appreciate the Dental solution. I am happy getting good traeatment. The have a good team. Really this is then best",
        "img":"https://health-center.vamtam.com/wp-content/uploads/2013/06/Untitled-1.jpg"
    },
    {
        "id":4,"name":"Jackulin","designation":"Engineer",
        "qoute":"I appreciate the Dental solution. I am happy getting good traeatment. The have a good team. Really this is then best",
        "img":"https://health-center.vamtam.com/wp-content/uploads/2013/07/tes2.jpg"
    }
    
]